Makefile
protos/README.md
protos/buf.lock
protos/buf.yaml
protos/cometbft/abci/v1/service.proto
protos/cometbft/abci/v1/types.proto
protos/cometbft/abci/v1beta1/types.proto
protos/cometbft/abci/v1beta2/types.proto
protos/cometbft/abci/v1beta3/types.proto
protos/cometbft/blocksync/v1/types.proto
protos/cometbft/blocksync/v1beta1/types.proto
protos/cometbft/consensus/v1/types.proto
protos/cometbft/consensus/v1/wal.proto
protos/cometbft/consensus/v1beta1/types.proto
protos/cometbft/consensus/v1beta1/wal.proto
protos/cometbft/crypto/v1/keys.proto
protos/cometbft/crypto/v1/proof.proto
protos/cometbft/libs/bits/v1/types.proto
protos/cometbft/mempool/v1/types.proto
protos/cometbft/p2p/v1/conn.proto
protos/cometbft/p2p/v1/pex.proto
protos/cometbft/p2p/v1/types.proto
protos/cometbft/privval/v1/types.proto
protos/cometbft/privval/v1beta1/types.proto
protos/cometbft/privval/v1beta2/types.proto
protos/cometbft/rpc/grpc/v1beta1/types.proto
protos/cometbft/rpc/grpc/v1beta2/types.proto
protos/cometbft/rpc/grpc/v1beta3/types.proto
protos/cometbft/services/block/v1/block.proto
protos/cometbft/services/block/v1/block_service.proto
protos/cometbft/services/block_results/v1/block_results.proto
protos/cometbft/services/block_results/v1/block_results_service.proto
protos/cometbft/services/pruning/v1/pruning.proto
protos/cometbft/services/pruning/v1/service.proto
protos/cometbft/services/version/v1/version.proto
protos/cometbft/services/version/v1/version_service.proto
protos/cometbft/state/v1/types.proto
protos/cometbft/state/v1beta1/types.proto
protos/cometbft/state/v1beta2/types.proto
protos/cometbft/state/v1beta3/types.proto
protos/cometbft/statesync/v1/types.proto
protos/cometbft/store/v1/types.proto
protos/cometbft/types/v1/block.proto
protos/cometbft/types/v1/canonical.proto
protos/cometbft/types/v1/events.proto
protos/cometbft/types/v1/evidence.proto
protos/cometbft/types/v1/params.proto
protos/cometbft/types/v1/types.proto
protos/cometbft/types/v1/validator.proto
xian_node-1.0.1.dist-info/LICENSE
xian_node-1.0.1.dist-info/METADATA
xian_node-1.0.1.dist-info/WHEEL
xian_node-1.0.1.dist-info/entry_points.txt
xian_node-1.0.1.dist-info/RECORD
